logicsdk/__init__.py
logicsdk/data_masking.py
logicsdk/main.py
logicsdk/nl2sql.py
logicsdk/structredExtraction.py
logicsdk/summarizer.py
logicsdk-0.0.9.dist-info/LICENSE
logicsdk-0.0.9.dist-info/METADATA
logicsdk-0.0.9.dist-info/WHEEL
logicsdk-0.0.9.dist-info/top_level.txt
logicsdk-0.0.9.dist-info/RECORD
