Metadata-Version: 2.1
Name: logicsdk
Version: 0.0.9
Summary: An avahiai library which makes your Gen-AI tasks effortless
Home-page: https://github.com/avahi-org/logicai.git
Author: Avahi AWS
Author-email: info@avahitech.com
License: MIT
Classifier: License :: OSI Approved :: MIT License
Classifier: Programming Language :: Python :: 3.9
Classifier: Operating System :: OS Independent
Requires-Python: >=3.9
License-File: LICENSE
Requires-Dist: boto3>=1.34.160
Requires-Dist: loguru>=0.7.2
Requires-Dist: python-docx>=1.1.2
Requires-Dist: PyMuPDF>=1.24.9
Requires-Dist: langchain>=0.1.12
Requires-Dist: langchain-community>=0.0.29
Requires-Dist: langchain-experimental>=0.0.54
Requires-Dist: psycopg2>=2.9.9
Requires-Dist: PyMySQL>=1.1.1
Provides-Extra: dev
Requires-Dist: twine>=4.0.2; extra == "dev"
